{
  "data": {
    "article": {},
    "attachments": {
      "media_keys": [
        "3_2005647067423854592"
      ]
    },
    "author_id": "1912063502782812160",
    "conversation_id": "2005647070385107410",
    "created_at": "2025-12-29T14:28:19.000Z",
    "edit_controls": {
      "editable_until": "2025-12-29T15:28:19.000Z",
      "edits_remaining": 5,
      "is_edit_eligible": true
    },
    "edit_history_tweet_ids": [
      "2005647070385107410"
    ],
    "entities": {
      "urls": [
        {
          "display_url": "pic.x.com/znwaWUrw6P",
          "end": 30,
          "expanded_url": "https://x.com/Ekouuuuuu/status/2005647070385107410/photo/1",
          "media_key": "3_2005647067423854592",
          "start": 7,
          "url": "https://t.co/znwaWUrw6P"
        }
      ]
    },
    "geo": {},
    "id": "2005647070385107410",
    "lang": "zh",
    "note_tweet": {
      "entities": {}
    },
    "possibly_sensitive": false,
    "public_metrics": {
      "bookmark_count": 0,
      "impression_count": 0,
      "like_count": 0,
      "quote_count": 0,
      "reply_count": 0,
      "retweet_count": 0
    },
    "reply_settings": "everyone",
    "text": "好無聊誰來玩 https://t.co/znwaWUrw6P"
  },
  "includes": {
    "media": [
      {
        "height": 988,
        "media_key": "3_2005647067423854592",
        "public_metrics": {},
        "type": "photo",
        "url": "https://pbs.twimg.com/media/G9V9YaaaUAAJ4F4.jpg",
        "width": 1008
      }
    ],
    "tweets": [
      {
        "article": {},
        "attachments": {
          "media_keys": [
            "3_2005647067423854592"
          ]
        },
        "author_id": "1912063502782812160",
        "conversation_id": "2005647070385107410",
        "created_at": "2025-12-29T14:28:19.000Z",
        "edit_controls": {
          "editable_until": "2025-12-29T15:28:19.000Z",
          "edits_remaining": 5,
          "is_edit_eligible": true
        },
        "edit_history_tweet_ids": [
          "2005647070385107410"
        ],
        "entities": {
          "urls": [
            {
              "display_url": "pic.x.com/znwaWUrw6P",
              "end": 30,
              "expanded_url": "https://x.com/Ekouuuuuu/status/2005647070385107410/photo/1",
              "media_key": "3_2005647067423854592",
              "start": 7,
              "url": "https://t.co/znwaWUrw6P"
            }
          ]
        },
        "geo": {},
        "id": "2005647070385107410",
        "lang": "zh",
        "note_tweet": {
          "entities": {}
        },
        "possibly_sensitive": false,
        "public_metrics": {
          "bookmark_count": 0,
          "impression_count": 0,
          "like_count": 0,
          "quote_count": 0,
          "reply_count": 0,
          "retweet_count": 0
        },
        "reply_settings": "everyone",
        "text": "好無聊誰來玩 https://t.co/znwaWUrw6P"
      }
    ],
    "users": [
      {
        "created_at": "2025-04-15T08:40:51.000Z",
        "description": "滿紙荒唐言一把辛酸淚‖叫我白菜就好了w‖生理性別女‖養病中…‖🇯🇵🤝🇹🇼‖厭惡一切高高在上的健全人‖悲憫一切逝者‖支畜滾‖同類互fo",
        "id": "1912063502782812160",
        "location": "罌粟花與你/",
        "name": "白菜Akina",
        "profile_image_url": "https://pbs.twimg.com/profile_images/1999521365557391360/nuwyWmKl_normal.jpg",
        "protected": false,
        "public_metrics": {
          "followers_count": 85,
          "following_count": 191,
          "like_count": 5288,
          "listed_count": 1,
          "media_count": 126,
          "tweet_count": 882
        },
        "username": "Ekouuuuuu",
        "verified": false
      }
    ]
  }
}