{
  "data": {
    "article": {},
    "attachments": {},
    "author_id": "1912063502782812160",
    "conversation_id": "2000155089588367375",
    "created_at": "2025-12-14T12:04:33.000Z",
    "edit_controls": {
      "editable_until": "2025-12-14T13:04:33.000Z",
      "edits_remaining": 5,
      "is_edit_eligible": false
    },
    "edit_history_tweet_ids": [
      "2000175071789482178"
    ],
    "entities": {
      "mentions": [
        {
          "end": 16,
          "id": "1531874456997863424",
          "start": 0,
          "username": "guodongmaikefe2"
        }
      ]
    },
    "geo": {},
    "id": "2000175071789482178",
    "in_reply_to_user_id": "1531874456997863424",
    "lang": "ja",
    "note_tweet": {
      "entities": {}
    },
    "possibly_sensitive": false,
    "public_metrics": {
      "bookmark_count": 0,
      "impression_count": 0,
      "like_count": 0,
      "quote_count": 0,
      "reply_count": 0,
      "retweet_count": 0
    },
    "referenced_tweets": [
      {
        "id": "2000155089588367375",
        "type": "replied_to"
      }
    ],
    "reply_settings": "everyone",
    "text": "@guodongmaikefe2 收到！"
  },
  "includes": {
    "tweets": [
      {
        "article": {},
        "attachments": {},
        "author_id": "1912063502782812160",
        "conversation_id": "2000155089588367375",
        "created_at": "2025-12-14T12:04:33.000Z",
        "edit_controls": {
          "editable_until": "2025-12-14T13:04:33.000Z",
          "edits_remaining": 5,
          "is_edit_eligible": false
        },
        "edit_history_tweet_ids": [
          "2000175071789482178"
        ],
        "entities": {
          "mentions": [
            {
              "end": 16,
              "id": "1531874456997863424",
              "start": 0,
              "username": "guodongmaikefe2"
            }
          ]
        },
        "geo": {},
        "id": "2000175071789482178",
        "in_reply_to_user_id": "1531874456997863424",
        "lang": "ja",
        "note_tweet": {
          "entities": {}
        },
        "possibly_sensitive": false,
        "public_metrics": {
          "bookmark_count": 0,
          "impression_count": 0,
          "like_count": 0,
          "quote_count": 0,
          "reply_count": 0,
          "retweet_count": 0
        },
        "referenced_tweets": [
          {
            "id": "2000155089588367375",
            "type": "replied_to"
          }
        ],
        "reply_settings": "everyone",
        "text": "@guodongmaikefe2 收到！"
      },
      {
        "article": {},
        "attachments": {},
        "author_id": "1531874456997863424",
        "conversation_id": "2000155089588367375",
        "created_at": "2025-12-14T10:45:09.000Z",
        "edit_controls": {
          "editable_until": "2025-12-14T11:45:09.000Z",
          "edits_remaining": 5,
          "is_edit_eligible": true
        },
        "edit_history_tweet_ids": [
          "2000155089588367375"
        ],
        "entities": {},
        "geo": {},
        "id": "2000155089588367375",
        "lang": "zh",
        "note_tweet": {
          "entities": {}
        },
        "possibly_sensitive": false,
        "public_metrics": {
          "bookmark_count": 0,
          "impression_count": 48,
          "like_count": 8,
          "quote_count": 0,
          "reply_count": 1,
          "retweet_count": 0
        },
        "reply_settings": "everyone",
        "text": "现在，所有人!爱老己!"
      }
    ],
    "users": [
      {
        "created_at": "2025-04-15T08:40:51.000Z",
        "description": "叫我白菜就好了w‖養病中……‖化學極樂‖🇯🇵🤝🇹🇼‖oder‖N₂O重度依賴‖支畜滾‖同類互fo",
        "id": "1912063502782812160",
        "location": "罌粟花與你/",
        "name": "白菜Akina",
        "pinned_tweet_id": "1999859855524565310",
        "profile_image_url": "https://pbs.twimg.com/profile_images/1999521365557391360/nuwyWmKl_normal.jpg",
        "protected": false,
        "public_metrics": {
          "followers_count": 59,
          "following_count": 153,
          "like_count": 3892,
          "listed_count": 1,
          "media_count": 67,
          "tweet_count": 504
        },
        "username": "Ekouuuuuu",
        "verified": false
      },
      {
        "created_at": "2022-06-01T05:45:36.000Z",
        "description": "不要被任何事物掌控/⌓‿⌓/抑郁焦虑/同类互fo/发癫/异性恋/由于被性骚扰过所以恐gay，恐跨/愈美片是屎/od就是吸毒所以我是个毒虫/",
        "id": "1531874456997863424",
        "location": "明天",
        "name": "不开心就od",
        "pinned_tweet_id": "1994668785635311976",
        "profile_image_url": "https://pbs.twimg.com/profile_images/1984521028274700291/SnoaoxPJ_normal.jpg",
        "protected": false,
        "public_metrics": {
          "followers_count": 238,
          "following_count": 167,
          "like_count": 10303,
          "listed_count": 0,
          "media_count": 162,
          "tweet_count": 950
        },
        "username": "guodongmaikefe2",
        "verified": false
      }
    ]
  }
}