{
  "data": {
    "article": {},
    "attachments": {},
    "author_id": "1912063502782812160",
    "conversation_id": "2000761554040442952",
    "created_at": "2025-12-16T02:55:01.000Z",
    "edit_controls": {
      "editable_until": "2025-12-16T03:55:01.000Z",
      "edits_remaining": 5,
      "is_edit_eligible": true
    },
    "edit_history_tweet_ids": [
      "2000761554040442952"
    ],
    "entities": {
      "urls": [
        {
          "display_url": "x.com/chijin99/statu…",
          "end": 86,
          "expanded_url": "https://twitter.com/chijin99/status/2000360217868116323",
          "start": 63,
          "url": "https://t.co/osAhF70Cvg"
        }
      ]
    },
    "geo": {},
    "id": "2000761554040442952",
    "lang": "zh",
    "note_tweet": {
      "entities": {}
    },
    "possibly_sensitive": false,
    "public_metrics": {
      "bookmark_count": 0,
      "impression_count": 0,
      "like_count": 0,
      "quote_count": 0,
      "reply_count": 0,
      "retweet_count": 0
    },
    "referenced_tweets": [
      {
        "id": "2000360217868116323",
        "type": "quoted"
      }
    ],
    "reply_settings": "everyone",
    "text": "唯一具有法律合法性能代表中國的有且僅有中華民國，因為在1912年清帝退位，傳於中華民國，而中共屬於武裝奪取政權，不具有合法性 https://t.co/osAhF70Cvg"
  },
  "includes": {
    "media": [
      {
        "height": 1034,
        "media_key": "3_2000360206954557441",
        "public_metrics": {},
        "type": "photo",
        "url": "https://pbs.twimg.com/media/G8K1AoZacAE0zrE.jpg",
        "width": 1024
      }
    ],
    "tweets": [
      {
        "article": {},
        "attachments": {},
        "author_id": "1912063502782812160",
        "conversation_id": "2000761554040442952",
        "created_at": "2025-12-16T02:55:01.000Z",
        "edit_controls": {
          "editable_until": "2025-12-16T03:55:01.000Z",
          "edits_remaining": 5,
          "is_edit_eligible": true
        },
        "edit_history_tweet_ids": [
          "2000761554040442952"
        ],
        "entities": {
          "urls": [
            {
              "display_url": "x.com/chijin99/statu…",
              "end": 86,
              "expanded_url": "https://twitter.com/chijin99/status/2000360217868116323",
              "start": 63,
              "url": "https://t.co/osAhF70Cvg"
            }
          ]
        },
        "geo": {},
        "id": "2000761554040442952",
        "lang": "zh",
        "note_tweet": {
          "entities": {}
        },
        "possibly_sensitive": false,
        "public_metrics": {
          "bookmark_count": 0,
          "impression_count": 0,
          "like_count": 0,
          "quote_count": 0,
          "reply_count": 0,
          "retweet_count": 0
        },
        "referenced_tweets": [
          {
            "id": "2000360217868116323",
            "type": "quoted"
          }
        ],
        "reply_settings": "everyone",
        "text": "唯一具有法律合法性能代表中國的有且僅有中華民國，因為在1912年清帝退位，傳於中華民國，而中共屬於武裝奪取政權，不具有合法性 https://t.co/osAhF70Cvg"
      },
      {
        "article": {},
        "attachments": {
          "media_keys": [
            "3_2000360206954557441"
          ]
        },
        "author_id": "1600695371659116545",
        "conversation_id": "2000360217868116323",
        "created_at": "2025-12-15T00:20:15.000Z",
        "edit_controls": {
          "editable_until": "2025-12-15T01:20:15.000Z",
          "edits_remaining": 5,
          "is_edit_eligible": true
        },
        "edit_history_tweet_ids": [
          "2000360217868116323"
        ],
        "entities": {
          "urls": [
            {
              "display_url": "pic.x.com/1bVX3o4SdM",
              "end": 23,
              "expanded_url": "https://x.com/chijin99/status/2000360217868116323/photo/1",
              "media_key": "3_2000360206954557441",
              "start": 0,
              "url": "https://t.co/1bVX3o4SdM"
            }
          ]
        },
        "geo": {},
        "id": "2000360217868116323",
        "lang": "zxx",
        "note_tweet": {
          "entities": {}
        },
        "possibly_sensitive": false,
        "public_metrics": {
          "bookmark_count": 10,
          "impression_count": 62233,
          "like_count": 391,
          "quote_count": 5,
          "reply_count": 36,
          "retweet_count": 45
        },
        "reply_settings": "everyone",
        "text": "https://t.co/1bVX3o4SdM"
      }
    ],
    "users": [
      {
        "created_at": "2025-04-15T08:40:51.000Z",
        "description": "叫我白菜就好了w‖養病中……‖化學極樂‖🇯🇵🤝🇹🇼‖oder‖N₂O重度依賴‖支畜滾‖同類互fo",
        "id": "1912063502782812160",
        "location": "罌粟花與你/",
        "name": "白菜Akina",
        "pinned_tweet_id": "1999859855524565310",
        "profile_image_url": "https://pbs.twimg.com/profile_images/1999521365557391360/nuwyWmKl_normal.jpg",
        "protected": false,
        "public_metrics": {
          "followers_count": 63,
          "following_count": 166,
          "like_count": 4079,
          "listed_count": 1,
          "media_count": 71,
          "tweet_count": 589
        },
        "username": "Ekouuuuuu",
        "verified": false
      },
      {
        "created_at": "2022-12-08T03:35:23.000Z",
        "description": "樹欲靜而風不止",
        "id": "1600695371659116545",
        "location": "悉尼",
        "name": "進",
        "pinned_tweet_id": "2000360217868116323",
        "profile_image_url": "https://pbs.twimg.com/profile_images/1600695509244874752/BSJKXO7H_normal.jpg",
        "protected": false,
        "public_metrics": {
          "followers_count": 4451,
          "following_count": 2087,
          "like_count": 10323,
          "listed_count": 16,
          "media_count": 391,
          "tweet_count": 2447
        },
        "username": "chijin99",
        "verified": true
      }
    ]
  }
}