{
  "data": {
    "article": {},
    "attachments": {
      "media_keys": [
        "3_2056068407637028864"
      ]
    },
    "author_id": "1912063502782812160",
    "conversation_id": "2056068409776058742",
    "created_at": "2026-05-17T17:44:43.000Z",
    "edit_controls": {
      "editable_until": "2026-05-17T18:44:43.000Z",
      "edits_remaining": 5,
      "is_edit_eligible": true
    },
    "edit_history_tweet_ids": [
      "2056068409776058742"
    ],
    "entities": {
      "urls": [
        {
          "display_url": "pic.x.com/8p3kyOMr4R",
          "end": 43,
          "expanded_url": "https://x.com/Ekouuuuuu/status/2056068409776058742/photo/1",
          "media_key": "3_2056068407637028864",
          "start": 20,
          "url": "https://t.co/8p3kyOMr4R"
        },
        {
          "display_url": "x.com/Ekouuuuuu/stat…",
          "end": 67,
          "expanded_url": "https://twitter.com/Ekouuuuuu/status/2056052956978631015",
          "start": 44,
          "url": "https://t.co/ks13NBKyU9"
        }
      ]
    },
    "geo": {},
    "id": "2056068409776058742",
    "lang": "zh",
    "note_tweet": {
      "entities": {}
    },
    "possibly_sensitive": false,
    "public_metrics": {
      "bookmark_count": 0,
      "impression_count": 0,
      "like_count": 1,
      "quote_count": 0,
      "reply_count": 0,
      "retweet_count": 0
    },
    "referenced_tweets": [
      {
        "id": "2056052956978631015",
        "type": "quoted"
      }
    ],
    "reply_settings": "everyone",
    "text": "我想在我的藥起效後我就什麼都不再需要了 https://t.co/8p3kyOMr4R https://t.co/ks13NBKyU9"
  },
  "includes": {
    "media": [
      {
        "height": 2048,
        "media_key": "3_2056068407637028864",
        "public_metrics": {},
        "type": "photo",
        "url": "https://pbs.twimg.com/media/HIifUr8bsAApzH5.jpg",
        "width": 922
      }
    ],
    "tweets": [
      {
        "article": {},
        "attachments": {
          "media_keys": [
            "3_2056068407637028864"
          ]
        },
        "author_id": "1912063502782812160",
        "conversation_id": "2056068409776058742",
        "created_at": "2026-05-17T17:44:43.000Z",
        "edit_controls": {
          "editable_until": "2026-05-17T18:44:43.000Z",
          "edits_remaining": 5,
          "is_edit_eligible": true
        },
        "edit_history_tweet_ids": [
          "2056068409776058742"
        ],
        "entities": {
          "urls": [
            {
              "display_url": "pic.x.com/8p3kyOMr4R",
              "end": 43,
              "expanded_url": "https://x.com/Ekouuuuuu/status/2056068409776058742/photo/1",
              "media_key": "3_2056068407637028864",
              "start": 20,
              "url": "https://t.co/8p3kyOMr4R"
            },
            {
              "display_url": "x.com/Ekouuuuuu/stat…",
              "end": 67,
              "expanded_url": "https://twitter.com/Ekouuuuuu/status/2056052956978631015",
              "start": 44,
              "url": "https://t.co/ks13NBKyU9"
            }
          ]
        },
        "geo": {},
        "id": "2056068409776058742",
        "lang": "zh",
        "note_tweet": {
          "entities": {}
        },
        "possibly_sensitive": false,
        "public_metrics": {
          "bookmark_count": 0,
          "impression_count": 0,
          "like_count": 1,
          "quote_count": 0,
          "reply_count": 0,
          "retweet_count": 0
        },
        "referenced_tweets": [
          {
            "id": "2056052956978631015",
            "type": "quoted"
          }
        ],
        "reply_settings": "everyone",
        "text": "我想在我的藥起效後我就什麼都不再需要了 https://t.co/8p3kyOMr4R https://t.co/ks13NBKyU9"
      },
      {
        "article": {},
        "attachments": {},
        "author_id": "1912063502782812160",
        "conversation_id": "2056052956978631015",
        "created_at": "2026-05-17T16:43:19.000Z",
        "edit_controls": {
          "editable_until": "2026-05-17T17:43:19.000Z",
          "edits_remaining": 5,
          "is_edit_eligible": true
        },
        "edit_history_tweet_ids": [
          "2056052956978631015"
        ],
        "entities": {},
        "geo": {},
        "id": "2056052956978631015",
        "lang": "zh",
        "note_tweet": {
          "entities": {}
        },
        "possibly_sensitive": false,
        "public_metrics": {
          "bookmark_count": 0,
          "impression_count": 17,
          "like_count": 1,
          "quote_count": 1,
          "reply_count": 0,
          "retweet_count": 0
        },
        "reply_settings": "everyone",
        "text": "我再也無法確定我需要什麼了\n可能是對我再也沒有惡意的幻境 不會再爭吵的家庭 一段什麼都不需要做也可以維持的關係 一個穩定的精神 一顆不會絞痛的心臟 一個挑不出錯的外貌 一張花不完的支票 還是一個不需要進行什麼糾結和苦痛就可以永遠消失的肉體和靈魂\n但我太貪心了\n所以什麼都沒有"
      }
    ],
    "users": [
      {
        "created_at": "2025-04-15T08:40:51.000Z",
        "description": "她說她停不下這瘋狂‖閨蜜@seeFvn‖老公@Shiroko_Li‖1/7/2024 DXM事變永遠懷念‖查主頁成分回fo",
        "entities": {
          "description": {
            "mentions": [
              {
                "end": 19,
                "start": 12,
                "username": "seeFvn"
              },
              {
                "end": 33,
                "start": 22,
                "username": "Shiroko_Li"
              }
            ]
          },
          "url": {
            "urls": [
              {
                "display_url": "t.me/Ekouuuuuu",
                "end": 23,
                "expanded_url": "http://t.me/Ekouuuuuu",
                "start": 0,
                "url": "https://t.co/8kuFPf6U23"
              }
            ]
          }
        },
        "id": "1912063502782812160",
        "location": "罌粟花與你/3lue",
        "name": "最後一朵 Mandrake",
        "pinned_tweet_id": "2054494874192195972",
        "profile_image_url": "https://pbs.twimg.com/profile_images/2044783933703823360/nX1HDqhs_normal.jpg",
        "protected": false,
        "public_metrics": {
          "followers_count": 182,
          "following_count": 297,
          "like_count": 12859,
          "listed_count": 1,
          "media_count": 524,
          "tweet_count": 3212
        },
        "url": "https://t.co/8kuFPf6U23",
        "username": "Ekouuuuuu",
        "verified": false
      }
    ]
  }
}